_libgcc_mutex/__init__.py
libgcc_mutex-0.1.0.dist-info/METADATA
libgcc_mutex-0.1.0.dist-info/WHEEL
libgcc_mutex-0.1.0.dist-info/top_level.txt
libgcc_mutex-0.1.0.dist-info/RECORD
