Metadata-Version: 2.4
Name: libgcc-mutex
Version: 0.1.0
Summary: Dummy _libgcc_mutex package for PyPI
Author-email: Your Name <you@example.com>
Requires-Python: >=3.7
